polars_schema_index-0.1.2.dist-info/METADATA
polars_schema_index-0.1.2.dist-info/WHEEL
polars_schema_index-0.1.2.dist-info/entry_points.txt
polars_schema_index-0.1.2.dist-info/licenses/LICENSE
polars_schema_index/__init__.py
polars_schema_index-0.1.2.dist-info/RECORD
